Metadata-Version: 1.0
Name: html-jparser
Version: 0.3
Summary: Easy html parser with Jquery selector
Home-page: https://github.com/FellowCode/html-jparser
Author: FellowCode
Author-email: sergo79_f1@mail.ru
License: UNKNOWN
Keywords: html parser jquery select easy
Platform: UNKNOWN
